adap/__init__.py
adap/adap.py
adap/example.py
adap/test.py
adap-0.0.1.dist-info/METADATA
adap-0.0.1.dist-info/WHEEL
adap-0.0.1.dist-info/licenses/LICENSE
adap-0.0.1.dist-info/RECORD
