Metadata-Version: 2.3
Name: adap
Version: 0.0.1
Summary: This is python package used detect different types of anomalies in compressors' sensors time series data.
Project-URL: Homepage, https://github.com/Wickramanayaka/adap.git
Project-URL: Issues, https://github.com/Wickramanayaka/adap.git/issues
Author-email: Chamal Ayesh Wickramanayaka <chamal.aw@live.com>
License-File: LICENSE
Classifier: License :: OSI Approved :: MIT License
Classifier: Operating System :: OS Independent
Classifier: Programming Language :: Python :: 3
Requires-Python: >=3.10
